[
    {
        "topic": "I noticed I lose motivation when a good streak starts feeling like something I have to protect",
        "subreddit": "r/motivation"
    },
    {
        "topic": "I noticed I lose discipline when I keep preparing for the version of the task that never actually happens",
        "subreddit": "r/getdisciplined"
    },
    {
        "topic": "I noticed I lose motivation when I keep moving the finish line after I’ve already done enough",
        "subreddit": "r/getmotivatedmindset"
    },
    {
        "topic": "I noticed I was losing motivation by turning every interest into a test of whether it was worth my time",
        "subreddit": "r/motivation"
    },
    {
        "topic": "I noticed I waste motivation trying to prove I’m committed before I actually build anything",
        "subreddit": "r/getmotivatedmindset"
    },
    {
        "topic": "I realized I wasn't addicted to my phone, I was addicted to never having an empty moment",
        "subreddit": "r/nosurf"
    },
    {
        "topic": "I noticed I lose motivation when I make the first step too easy to avoid",
        "subreddit": "r/motivation"
    },
    {
        "topic": "I noticed I was breaking my routines by negotiating with myself over tiny exceptions",
        "subreddit": "r/getdisciplined"
    },
    {
        "topic": "I noticed I lose motivation when I keep trying to protect my confidence before I actually earn it",
        "subreddit": "r/getmotivatedmindset"
    },
    {
        "topic": "I noticed I lose motivation when my goal starts becoming part of my identity",
        "subreddit": "r/motivation"
    },
    {
        "topic": "I noticed I lose motivation when my progress becomes visible to me",
        "subreddit": "r/getmotivatedmindset"
    },
    {
        "topic": "I noticed I was more addicted to fresh starts than actually staying consistent",
        "subreddit": "r/getdisciplined"
    },
    {
        "topic": "I noticed I lose discipline when I keep too many tiny decisions hanging over me",
        "subreddit": "r/getdisciplined"
    },
    {
        "topic": "I noticed I lose discipline when I make a task feel like a test of who I am",
        "subreddit": "r/getdisciplined"
    },
    {
        "topic": "I noticed I lose discipline when I start managing my rest like it’s another project to optimize",
        "subreddit": "r/getdisciplined"
    },
    {
        "topic": "I noticed I only do my best work when I tell myself it doesn’t count yet",
        "subreddit": "r/getdisciplined"
    },
    {
        "topic": "I noticed I lose momentum the moment I explain my plan to someone who didn’t even ask",
        "subreddit": "r/motivation"
    },
    {
        "topic": "I noticed I only start doubting myself the moment I try to guess how long it will take me",
        "subreddit": "r/getmotivatedmindset"
    },
    {
        "topic": "I noticed I stop working right after I finally understand what I’m doing",
        "subreddit": "r/motivation"
    },
    {
        "topic": "I don’t really scroll for content anymore, I keep reopening apps to check if anything changed since I last looked",
        "subreddit": "r/nosurf"
    },
    {
        "topic": "I noticed I work fine until I decide a task is actually important",
        "subreddit": "r/motivation"
    },
    {
        "topic": "I noticed I work fine until I reopen something I left unfinished, then I suddenly can’t continue",
        "subreddit": "r/getmotivatedmindset"
    },
    {
        "topic": "I noticed I stop working the moment my setup starts looking ‘finished’, even if I’m not actually done",
        "subreddit": "r/getdisciplined"
    },
    {
        "topic": "I noticed I don’t quit tasks when they get hard — I quit when I start getting slightly worse at them",
        "subreddit": "r/getmotivatedmindset"
    },
    {
        "topic": "I noticed I spent more energy redesigning my plan than actually testing whether it worked",
        "subreddit": "r/getmotivatedmindset"
    },
    {
        "topic": "I kept losing momentum right after finishing tiny tasks, not during the hard work itself",
        "subreddit": "r/motivation"
    },
    {
        "topic": "I thought I was disciplined in the mornings, but I was actually just undoing it every night at 11:30",
        "subreddit": "r/getmotivatedmindset"
    },
    {
        "topic": "I kept waiting to feel motivated, but the people I admired seemed to start while still annoyed",
        "subreddit": "r/motivation"
    },
    {
        "topic": "I realized most of my scrolling wasn't replacing activities, it was replacing transitions",
        "subreddit": "r/nosurf"
    },
    {
        "topic": "I stopped trying to fix my motivation and noticed the real problem was what happened right before I started",
        "subreddit": "r/getmotivatedmindset"
    }
]