{
    "content_generated": false,
    "post_to_comment_found": true,
    "link_to_post_to_comment": "https://www.reddit.com/r/nosurf/comments/1umhj8a/",
    "content_of_post_to_comment": "I'm from the UK, which is currently having a u-16 social media ban brought in next year, however it's been done in such a sloppy and awful way that it's really nothing more than an easily circumventable data collection drive.\n\nI was thinking for a while about a smartphone ban for under-18s. It could be harder to circumvent whilst also being more respectful of people's data.\n\nThe way I envisioned it was that smartphones (defined as devices with sim slots and the possibility of downloading applications or something to that style) would require proof of age at purchase, whether online or in store. A fine for provision of a smartphone could also exist to discourage parents from buying them for their kids, combined with seizure of said smartphone.\n\nThis would not only reduce the amount of teens and kids with smartphones but also reduce the issues that come with them like sexting, social media addiction, hazardous 'trends', crossing the road without looking, antisocial behaviour in public in pursuit of likes, and so on. Of course it wouldn't completely remove it, just like bans on underage drinking or underage driving haven't removed it either, but it would probably drastically reduce it.\n\nOnto the beneficial for our movement/community part, it would likely result in more dumbphones being made, some of which would probably be perfectly fine for usage by adults as teens don't want to buy things that come off as 'childish'. It would also probably reduce the social pressure of owning a smartphone as not owning one would be seen as perfectly standard, and smartphones would likely be seen as potential mental health hazards.\n\nIt would also likely reduce smartphone usage amongst young adults, the same way that those who didn't drink/smoke/take drugs during childhood have a lower risk of becoming addicted to said substances.",
    "comment_generated": false,
    "comment": ""
}